Tki/KiCore.py
Tki/KiFont.py
Tki/KiWidgets.py
Tki/__init__.py
Toolkit_InterFace-0.3.dist-info/LICENSE
Toolkit_InterFace-0.3.dist-info/METADATA
Toolkit_InterFace-0.3.dist-info/WHEEL
Toolkit_InterFace-0.3.dist-info/top_level.txt
Toolkit_InterFace-0.3.dist-info/RECORD
