Metadata-Version: 2.1
Name: Toolkit-InterFace
Version: 0.3
Summary: Tkinter Box
Home-page: https://github.com/XiangQinxi/Tki
Author: XiangQinxi
Author-email: XiangQinxi@outlook.com
License: MIT
Project-URL: Bug Tracker, https://github.com/XiangQinxi
Platform: UNKNOWN
Classifier: Programming Language :: Python :: 3.6
Classifier: Programming Language :: Python :: 3.7
Classifier: Programming Language :: Python :: 3.8
Classifier: Programming Language :: Python :: 3.9
Classifier: Programming Language :: Python :: 3.10
Classifier: Programming Language :: Python :: 3.11
Classifier: Programming Language :: Tcl
Classifier: License :: OSI Approved :: MIT License
Classifier: Development Status :: 4 - Beta
Classifier: License :: Freeware
Classifier: License :: OSI Approved :: MIT License
Classifier: Operating System :: MacOS
Classifier: Operating System :: Microsoft
Classifier: Operating System :: Unix
Classifier: Operating System :: OS Independent
Requires-Python: >=3.6
License-File: LICENSE
